LICENSE
MANIFEST.in
README
setup.cfg
setup.py
cube_business_ops/ConfigManager.py
cube_business_ops/Cubelog.py
cube_business_ops/OPSManager.py
cube_business_ops/__init__.py
cube_business_ops/properties.json
cube_business_ops.egg-info/PKG-INFO
cube_business_ops.egg-info/SOURCES.txt
cube_business_ops.egg-info/dependency_links.txt
cube_business_ops.egg-info/requires.txt
cube_business_ops.egg-info/top_level.txt
cube_business_ops/Checkers/Bizops_Checker.py
cube_business_ops/Checkers/__init__.py
cube_business_ops/LogHandlers/LogToDisk.py
cube_business_ops/LogHandlers/LogToPoDD.py
cube_business_ops/LogHandlers/__init__.py